{
  "personas": {
    "sarah": {
      "id": "sarah",
      "name": "Sarah Martinez",
      "title": "Production Builder",
      "description": "Managing 12 spec homes per year",
      "attributes": {
        "construction_phase": "foundation_framing",
        "customer_tier": "Production-Builder"
      }
    },
    "marcus": {
      "id": "marcus",
      "name": "Marcus Johnson",
      "title": "General Contractor",
      "description": "Custom homes and major renovations",
      "attributes": {
        "construction_phase": "foundation_framing",
        "quality_tier": "professional",
        "customer_tier": "Trade-Professional"
      }
    },
    "lisa": {
      "id": "lisa",
      "name": "Lisa Chen",
      "title": "Remodeling Contractor",
      "description": "High-end residential remodels",
      "attributes": {
        "package_tier": "better",
        "room_category": "bathroom",
        "customer_tier": "Trade-Professional"
      }
    },
    "david": {
      "id": "david",
      "name": "David Thompson",
      "title": "Pro Homeowner",
      "description": "DIY enthusiast building a deck",
      "attributes": {
        "deck_compatible": true,
        "deck_shape": "rectangular",
        "deck_material_type": "composite",
        "customer_tier": "Retail-Registered"
      }
    },
    "kevin": {
      "id": "kevin",
      "name": "Kevin Rodriguez",
      "title": "Store Manager",
      "description": "Managing inventory for pro contractor store",
      "attributes": {
        "store_velocity_category": "high_volume",
        "restock_priority": "high",
        "customer_tier": "Wholesale-Reseller"
      }
    }
  },
  "templates": [
    {
      "id": "sedona",
      "name": "The Sedona",
      "description": "2-story single-family home with optional bonus room",
      "sqft": 2450,
      "stories": 2,
      "bedrooms": 4,
      "bathrooms": 2.5,
      "image": "/images/floor-plans/sedona.png",
      "finishedImage": "/images/finished-homes/sedona.jpg",
      "variants": [
        {
          "id": "standard",
          "name": "Standard",
          "description": "Base 2,450 sqft layout"
        },
        {
          "id": "bonus_room",
          "name": "With Bonus Room",
          "description": "Adds 800 sqft bonus room above garage",
          "additionalSqft": 800
        }
      ],
      "phases": [
        {
          "phase": "foundation_framing",
          "name": "Foundation & Framing",
          "week": 1,
          "products": [
            {
              "sku": "LBR-D0414F1E",
              "name": "ToughGrip 2x4 Stud - 8ft",
              "quantity": 1,
              "multiplier": "per_unit"
            },
            {
              "sku": "LBR-2EBB314A",
              "name": "SafeGuard 2x6 Stud - 8ft",
              "quantity": 1,
              "multiplier": "per_unit"
            },
            {
              "sku": "LBR-26852468",
              "name": "PremiumBuild 2x8 Joist - 10ft",
              "quantity": 1,
              "multiplier": "per_unit"
            },
            {
              "sku": "LBR-2D637246",
              "name": "SafeGuard 2x10 Joist - 12ft",
              "quantity": 1,
              "multiplier": "per_unit"
            },
            {
              "sku": "LBR-96F409FB",
              "name": "PremiumBuild 2x12 Beam - 16ft",
              "quantity": 1,
              "multiplier": "per_unit"
            },
            {
              "sku": "LBR-9D32768F",
              "name": "ProFrame 4x4 Post - 8ft",
              "quantity": 1,
              "multiplier": "per_unit"
            },
            {
              "sku": "PLY-3C2EC476",
              "name": "ReliaBuild T&G Subfloor 3/4\" - 4x8",
              "quantity": 1,
              "multiplier": "per_unit"
            },
            {
              "sku": "STUD-44C79532",
              "name": "SafeGuard Metal Stud 20ga - 3.5\" x 10ft",
              "quantity": 1,
              "multiplier": "per_unit"
            },
            {
              "sku": "STUD-B6E3E673",
              "name": "DuraBuilt Metal Stud 20ga - 6\" x 10ft",
              "quantity": 1,
              "multiplier": "per_unit"
            },
            {
              "sku": "STUD-95E9D258",
              "name": "FastenPro Metal Track 20ga - 3.5\" x 10ft",
              "quantity": 1,
              "multiplier": "per_unit"
            },
            {
              "sku": "STUD-984F2EC0",
              "name": "FastenPro Metal Track 20ga - 6\" x 10ft",
              "quantity": 1,
              "multiplier": "per_unit"
            },
            {
              "sku": "DRYWALL-1E512505",
              "name": "DuraBuilt Fire Rated Drywall - 4x8",
              "quantity": 1,
              "multiplier": "per_unit"
            },
            {
              "sku": "NAIL-244FD20C",
              "name": "ReliaBuild Framing Nails 16d - 50lb Box",
              "quantity": 1,
              "multiplier": "per_unit"
            },
            {
              "sku": "NAIL-65F44C61",
              "name": "StructureMaster Concrete Nails - 5lb Box",
              "quantity": 1,
              "multiplier": "per_unit"
            },
            {
              "sku": "SCREW-4DC6B336",
              "name": "SafeGuard Self-Drilling Screws - 1lb",
              "quantity": 1,
              "multiplier": "per_unit"
            }
          ]
        },
        {
          "phase": "envelope",
          "name": "Building Envelope",
          "week": 3,
          "products": [
            {
              "sku": "PLY-7D58FF99",
              "name": "MaxStrength OSB Sheathing 7/16\" - 4x8",
              "quantity": 1,
              "multiplier": "per_unit"
            },
            {
              "sku": "PLY-AF7C8BA7",
              "name": "PremiumBuild CDX Plywood 1/2\" - 4x8",
              "quantity": 1,
              "multiplier": "per_unit"
            },
            {
              "sku": "PLY-2BA5387B",
              "name": "ReliaBuild Marine Plywood 3/4\" - 4x8",
              "quantity": 1,
              "multiplier": "per_unit"
            },
            {
              "sku": "PLY-E0240635",
              "name": "BuildRight Pro Siding Panel 3/8\" - 4x8",
              "quantity": 1,
              "multiplier": "per_unit"
            },
            {
              "sku": "WINDOW-8039584D",
              "name": "BuildRight Pro Single Hung Window - 36\"x48\"",
              "quantity": 1,
              "multiplier": "per_unit"
            },
            {
              "sku": "WINDOW-6642736C",
              "name": "StructureMaster Double Hung Window - 36\"x60\"",
              "quantity": 1,
              "multiplier": "per_unit"
            },
            {
              "sku": "WINDOW-8F26E917",
              "name": "MaxStrength Casement Window - 30\"x48\"",
              "quantity": 1,
              "multiplier": "per_unit"
            },
            {
              "sku": "WINDOW-51CD3FC4",
              "name": "BuildRight Pro Bay Window - 72\"x48\"",
              "quantity": 1,
              "multiplier": "per_unit"
            },
            {
              "sku": "WINDOW-5946F85C",
              "name": "FastenPro Awning Window - 36\"x24\"",
              "quantity": 1,
              "multiplier": "per_unit"
            },
            {
              "sku": "DOOR-34C72FD2",
              "name": "FastenPro Entry Door - Steel 36\"x80\"",
              "quantity": 1,
              "multiplier": "per_unit"
            }
          ]
        }
      ]
    }
  ],
  "packages": {
    "bathroom": [
      {
        "id": "bathroom-good",
        "tier": "good",
        "name": "Good Package",
        "type": "bathroom_remodel",
        "price": 8500,
        "image": "/images/packages/bathroom-good.jpg",
        "products": [],
        "features": [
          "Builder-grade fixtures",
          "Standard bathtub",
          "Laminate vanity",
          "Ceramic tile"
        ]
      },
      {
        "id": "bathroom-better",
        "tier": "better",
        "name": "Better Package",
        "type": "bathroom_remodel",
        "price": 14200,
        "image": "/images/packages/bathroom-better.jpg",
        "products": [],
        "features": [
          "Mid-range fixtures",
          "Acrylic tub",
          "Semi-custom vanity",
          "Porcelain tile"
        ]
      },
      {
        "id": "bathroom-best",
        "tier": "best",
        "name": "Best Package",
        "type": "bathroom_remodel",
        "price": 23800,
        "image": "/images/packages/bathroom-best.jpg",
        "products": [],
        "features": [
          "Premium fixtures",
          "Soaking tub",
          "Custom vanity",
          "Natural stone tile"
        ]
      }
    ]
  },
  "deckKits": [
    {
      "id": "deck-16x20-composite",
      "name": "16x20 Composite Deck Kit",
      "type": "deck",
      "shape": "rectangular",
      "material": "composite",
      "dimensions": {
        "width": 16,
        "depth": 20,
        "sqft": 320
      },
      "price": 6817,
      "image": "/images/kits/deck-composite.jpg",
      "products": [],
      "features": [
        "Low maintenance composite decking",
        "Aluminum railing system",
        "Hidden fastener system",
        "LED post cap lights",
        "Complete hardware kit",
        "Installation guide included"
      ],
      "requirements": [
        "Intermediate DIY skill level",
        "4-6 weekend project",
        "Basic tools required"
      ],
      "notIncluded": [
        "Concrete mix for footings",
        "Post-hole digger",
        "Power tools"
      ]
    }
  ],
  "restockCategories": [
    {
      "id": "restock-high",
      "velocityCategory": "high",
      "name": "High Velocity Items",
      "frequency": "2-3 times per week",
      "products": [
        {
          "sku": "LBR-D0414F1E",
          "name": "ToughGrip 2x4 Stud - 8ft",
          "currentStock": 46,
          "recommendedStock": "100",
          "daysSupply": "7",
          "velocityCategory": "high",
          "restockPriority": "high"
        },
        {
          "sku": "PLY-7D58FF99",
          "name": "MaxStrength OSB Sheathing 7/16\" - 4x8",
          "currentStock": 27,
          "recommendedStock": "Premium quality",
          "daysSupply": "7",
          "velocityCategory": "high",
          "restockPriority": "high"
        },
        {
          "sku": "PLY-AF7C8BA7",
          "name": "PremiumBuild CDX Plywood 1/2\" - 4x8",
          "currentStock": 47,
          "recommendedStock": "40",
          "daysSupply": "7",
          "velocityCategory": "high",
          "restockPriority": "high"
        },
        {
          "sku": "PLY-E0240635",
          "name": "BuildRight Pro Siding Panel 3/8\" - 4x8",
          "currentStock": 46,
          "recommendedStock": "25",
          "daysSupply": "14",
          "velocityCategory": "high",
          "restockPriority": "medium"
        },
        {
          "sku": "DRYWALL-8F034793",
          "name": "ProFrame Drywall 1/2\" - 4x8",
          "currentStock": 43,
          "recommendedStock": "60",
          "daysSupply": "7",
          "velocityCategory": "high",
          "restockPriority": "high"
        },
        {
          "sku": "DRYWALL-A8217B48",
          "name": "ProFrame Drywall 5/8\" - 4x8",
          "currentStock": 41,
          "recommendedStock": "50",
          "daysSupply": "7",
          "velocityCategory": "high",
          "restockPriority": "high"
        },
        {
          "sku": "DOOR-89357B1F",
          "name": "PremiumBuild Interior Door - Hollow Core 32\"x80\"",
          "currentStock": 11,
          "recommendedStock": "25",
          "daysSupply": "Professional grade",
          "velocityCategory": "high",
          "restockPriority": "high"
        },
        {
          "sku": "NAIL-244FD20C",
          "name": "ReliaBuild Framing Nails 16d - 50lb Box",
          "currentStock": 26,
          "recommendedStock": "30",
          "daysSupply": "7",
          "velocityCategory": "high",
          "restockPriority": "high"
        },
        {
          "sku": "NAIL-9D448DAA",
          "name": "ToughGrip Finish Nails 8d - 5lb Box",
          "currentStock": 42,
          "recommendedStock": "40",
          "daysSupply": "7",
          "velocityCategory": "high",
          "restockPriority": "high"
        },
        {
          "sku": "NAIL-2DBD44A2",
          "name": "DuraBuilt Roofing Nails - 50lb Box",
          "currentStock": 34,
          "recommendedStock": "25",
          "daysSupply": "7",
          "velocityCategory": "high",
          "restockPriority": "high"
        },
        {
          "sku": "NAIL-65F44C61",
          "name": "StructureMaster Concrete Nails - 5lb Box",
          "currentStock": 4,
          "recommendedStock": "20",
          "daysSupply": "14",
          "velocityCategory": "high",
          "restockPriority": "medium"
        },
        {
          "sku": "SCREW-48C3413B",
          "name": "PremiumBuild Deck Screws #8 - 5lb Box",
          "currentStock": 19,
          "recommendedStock": "35",
          "daysSupply": "7",
          "velocityCategory": "high",
          "restockPriority": "high"
        },
        {
          "sku": "SCREW-704B6626",
          "name": "ToughGrip Drywall Screws - 5lb Box",
          "currentStock": 38,
          "recommendedStock": "50",
          "daysSupply": "7",
          "velocityCategory": "high",
          "restockPriority": "low"
        },
        {
          "sku": "SCREW-AD274060",
          "name": "ProFrame Wood Screws #10 - 1lb Box",
          "currentStock": 18,
          "recommendedStock": "Standard",
          "daysSupply": "7",
          "velocityCategory": "high",
          "restockPriority": "high"
        },
        {
          "sku": "SCREW-0DAA49A4",
          "name": "PremiumBuild Lag Screws 1/2\" - 50ct",
          "currentStock": 29,
          "recommendedStock": "15",
          "daysSupply": "Premium quality",
          "velocityCategory": "high",
          "restockPriority": "low"
        },
        {
          "sku": "ROOF-23151318",
          "name": "SafeGuard Asphalt Shingles 3-Tab - Bundle",
          "currentStock": 7,
          "recommendedStock": "40",
          "daysSupply": "7",
          "velocityCategory": "high",
          "restockPriority": "high"
        },
        {
          "sku": "ROOF-D793BF8B",
          "name": "ToughGrip Architectural Shingles - Bundle",
          "currentStock": 5,
          "recommendedStock": "35",
          "daysSupply": "7",
          "velocityCategory": "high",
          "restockPriority": "high"
        },
        {
          "sku": "ROOF-905BF883",
          "name": "BuildRight Pro Roofing Felt 15lb - Roll",
          "currentStock": 10,
          "recommendedStock": "30",
          "daysSupply": "7",
          "velocityCategory": "high",
          "restockPriority": "high"
        }
      ]
    },
    {
      "id": "restock-medium",
      "velocityCategory": "medium",
      "name": "Medium Velocity Items",
      "frequency": "Weekly",
      "products": [
        {
          "sku": "LBR-26852468",
          "name": "PremiumBuild 2x8 Joist - 10ft",
          "currentStock": 30,
          "recommendedStock": "50",
          "daysSupply": "14",
          "velocityCategory": "medium",
          "restockPriority": "medium"
        },
        {
          "sku": "LBR-2D637246",
          "name": "SafeGuard 2x10 Joist - 12ft",
          "currentStock": 16,
          "recommendedStock": "40",
          "daysSupply": "14",
          "velocityCategory": "medium",
          "restockPriority": "medium"
        },
        {
          "sku": "LBR-9D32768F",
          "name": "ProFrame 4x4 Post - 8ft",
          "currentStock": 32,
          "recommendedStock": "30",
          "daysSupply": "14",
          "velocityCategory": "medium",
          "restockPriority": "medium"
        },
        {
          "sku": "PLY-3C2EC476",
          "name": "ReliaBuild T&G Subfloor 3/4\" - 4x8",
          "currentStock": 43,
          "recommendedStock": "30",
          "daysSupply": "14",
          "velocityCategory": "medium",
          "restockPriority": "medium"
        },
        {
          "sku": "STUD-44C79532",
          "name": "SafeGuard Metal Stud 20ga - 3.5\" x 10ft",
          "currentStock": 2,
          "recommendedStock": "50",
          "daysSupply": "Professional grade",
          "velocityCategory": "medium",
          "restockPriority": "medium"
        },
        {
          "sku": "STUD-B6E3E673",
          "name": "DuraBuilt Metal Stud 20ga - 6\" x 10ft",
          "currentStock": 19,
          "recommendedStock": "40",
          "daysSupply": "14",
          "velocityCategory": "medium",
          "restockPriority": "medium"
        },
        {
          "sku": "STUD-95E9D258",
          "name": "FastenPro Metal Track 20ga - 3.5\" x 10ft",
          "currentStock": 6,
          "recommendedStock": "Standard",
          "daysSupply": "14",
          "velocityCategory": "medium",
          "restockPriority": "medium"
        },
        {
          "sku": "STUD-984F2EC0",
          "name": "FastenPro Metal Track 20ga - 6\" x 10ft",
          "currentStock": 32,
          "recommendedStock": "35",
          "daysSupply": "14",
          "velocityCategory": "medium",
          "restockPriority": "critical"
        },
        {
          "sku": "DRYWALL-67027AF0",
          "name": "BuildRight Pro Moisture Resistant Drywall - 4x8",
          "currentStock": 45,
          "recommendedStock": "30",
          "daysSupply": "14",
          "velocityCategory": "medium",
          "restockPriority": "medium"
        },
        {
          "sku": "DRYWALL-038C3C6C",
          "name": "StructureMaster Cement Board 1/2\" - 3x5",
          "currentStock": 47,
          "recommendedStock": "25",
          "daysSupply": "Standard",
          "velocityCategory": "medium",
          "restockPriority": "medium"
        },
        {
          "sku": "WINDOW-8039584D",
          "name": "BuildRight Pro Single Hung Window - 36\"x48\"",
          "currentStock": 13,
          "recommendedStock": "15",
          "daysSupply": "14",
          "velocityCategory": "medium",
          "restockPriority": "low"
        },
        {
          "sku": "WINDOW-6642736C",
          "name": "StructureMaster Double Hung Window - 36\"x60\"",
          "currentStock": 45,
          "recommendedStock": "12",
          "daysSupply": "14",
          "velocityCategory": "medium",
          "restockPriority": "medium"
        },
        {
          "sku": "WINDOW-888AFAE6",
          "name": "FastenPro Sliding Window - 48\"x36\"",
          "currentStock": 10,
          "recommendedStock": "10",
          "daysSupply": "14",
          "velocityCategory": "medium",
          "restockPriority": "medium"
        },
        {
          "sku": "DOOR-34C72FD2",
          "name": "FastenPro Entry Door - Steel 36\"x80\"",
          "currentStock": 7,
          "recommendedStock": "10",
          "daysSupply": "14",
          "velocityCategory": "medium",
          "restockPriority": "medium"
        },
        {
          "sku": "DOOR-75F9C73D",
          "name": "DuraBuilt Bi-fold Closet Door - 36\"x80\"",
          "currentStock": 48,
          "recommendedStock": "15",
          "daysSupply": "14",
          "velocityCategory": "medium",
          "restockPriority": "medium"
        },
        {
          "sku": "NAIL-D27A9BC3",
          "name": "MaxStrength Brad Nails 18ga - 5000ct",
          "currentStock": 24,
          "recommendedStock": "35",
          "daysSupply": "14",
          "velocityCategory": "medium",
          "restockPriority": "medium"
        },
        {
          "sku": "NAIL-7AD0771D",
          "name": "ToughGrip Ring Shank Nails - 25lb Box",
          "currentStock": 11,
          "recommendedStock": "20",
          "daysSupply": "14",
          "velocityCategory": "medium",
          "restockPriority": "medium"
        },
        {
          "sku": "SCREW-4DC6B336",
          "name": "SafeGuard Self-Drilling Screws - 1lb",
          "currentStock": 6,
          "recommendedStock": "30",
          "daysSupply": "14",
          "velocityCategory": "medium",
          "restockPriority": "low"
        },
        {
          "sku": "SCREW-A3256812",
          "name": "ToughGrip Cabinet Screws - 100ct",
          "currentStock": 6,
          "recommendedStock": "25",
          "daysSupply": "14",
          "velocityCategory": "medium",
          "restockPriority": "medium"
        },
        {
          "sku": "ROOF-7B1F4022",
          "name": "SafeGuard Premium Designer Shingles - Bundle",
          "currentStock": 18,
          "recommendedStock": "20",
          "daysSupply": "14",
          "velocityCategory": "medium",
          "restockPriority": "medium"
        }
      ]
    },
    {
      "id": "restock-low",
      "velocityCategory": "low",
      "name": "Low Velocity Items",
      "frequency": "As needed",
      "products": [
        {
          "sku": "LBR-2EBB314A",
          "name": "SafeGuard 2x6 Stud - 8ft",
          "currentStock": 5,
          "recommendedStock": "75",
          "daysSupply": "7",
          "velocityCategory": "low",
          "restockPriority": "high"
        },
        {
          "sku": "LBR-96F409FB",
          "name": "PremiumBuild 2x12 Beam - 16ft",
          "currentStock": 32,
          "recommendedStock": "20",
          "daysSupply": "30",
          "velocityCategory": "low",
          "restockPriority": "low"
        },
        {
          "sku": "PLY-2BA5387B",
          "name": "ReliaBuild Marine Plywood 3/4\" - 4x8",
          "currentStock": 33,
          "recommendedStock": "10",
          "daysSupply": "30",
          "velocityCategory": "low",
          "restockPriority": "low"
        },
        {
          "sku": "PLY-4C31A6A6",
          "name": "DuraBuilt Hardwood Plywood 1/4\" - 4x8",
          "currentStock": 38,
          "recommendedStock": "15",
          "daysSupply": "30",
          "velocityCategory": "low",
          "restockPriority": "low"
        },
        {
          "sku": "STUD-8DEC7739",
          "name": "StructureMaster Steel C-Channel - 8ft",
          "currentStock": 36,
          "recommendedStock": "20",
          "daysSupply": "30",
          "velocityCategory": "low",
          "restockPriority": "low"
        },
        {
          "sku": "STUD-07E7F7E4",
          "name": "ToughGrip Hat Channel - 12ft",
          "currentStock": 14,
          "recommendedStock": "25",
          "daysSupply": "30",
          "velocityCategory": "low",
          "restockPriority": "low"
        },
        {
          "sku": "DRYWALL-1E512505",
          "name": "DuraBuilt Fire Rated Drywall - 4x8",
          "currentStock": 21,
          "recommendedStock": "20",
          "daysSupply": "30",
          "velocityCategory": "low",
          "restockPriority": "low"
        },
        {
          "sku": "DRYWALL-439D9A62",
          "name": "MaxStrength Sound Dampening Drywall - 4x8",
          "currentStock": 37,
          "recommendedStock": "15",
          "daysSupply": "30",
          "velocityCategory": "low",
          "restockPriority": "low"
        },
        {
          "sku": "WINDOW-8F26E917",
          "name": "MaxStrength Casement Window - 30\"x48\"",
          "currentStock": 27,
          "recommendedStock": "8",
          "daysSupply": "30",
          "velocityCategory": "low",
          "restockPriority": "low"
        },
        {
          "sku": "WINDOW-51CD3FC4",
          "name": "BuildRight Pro Bay Window - 72\"x48\"",
          "currentStock": 20,
          "recommendedStock": "5",
          "daysSupply": "30",
          "velocityCategory": "low",
          "restockPriority": "low"
        },
        {
          "sku": "WINDOW-5946F85C",
          "name": "FastenPro Awning Window - 36\"x24\"",
          "currentStock": 43,
          "recommendedStock": "10",
          "daysSupply": "30",
          "velocityCategory": "low",
          "restockPriority": "low"
        },
        {
          "sku": "DOOR-070629C1",
          "name": "ToughGrip French Door - 60\"x80\"",
          "currentStock": 27,
          "recommendedStock": "5",
          "daysSupply": "30",
          "velocityCategory": "low",
          "restockPriority": "low"
        },
        {
          "sku": "DOOR-E93CC71C",
          "name": "StructureMaster Sliding Patio Door - 72\"x80\"",
          "currentStock": 32,
          "recommendedStock": "5",
          "daysSupply": "30",
          "velocityCategory": "low",
          "restockPriority": "low"
        },
        {
          "sku": "DOOR-81B579D4",
          "name": "BuildRight Pro Storm Door - 36\"x80\"",
          "currentStock": 22,
          "recommendedStock": "8",
          "daysSupply": "30",
          "velocityCategory": "low",
          "restockPriority": "low"
        },
        {
          "sku": "ROOF-A8DE0B49",
          "name": "DuraBuilt Self-Adhering Underlayment - Roll",
          "currentStock": 46,
          "recommendedStock": "10",
          "daysSupply": "30",
          "velocityCategory": "low",
          "restockPriority": "low"
        },
        {
          "sku": "ROOF-05516930",
          "name": "MaxStrength Ventilated Underlayment - Roll",
          "currentStock": 26,
          "recommendedStock": "10",
          "daysSupply": "30",
          "velocityCategory": "low",
          "restockPriority": "low"
        }
      ]
    }
  ],
  "metadata": {
    "generated": "2025-11-26T06:13:23.846Z",
    "version": "2.0",
    "source": "buildright-aco"
  }
}